peeve.py
peeve-0.2.0.dist-info/METADATA
peeve-0.2.0.dist-info/WHEEL
peeve-0.2.0.dist-info/entry_points.txt
peeve-0.2.0.dist-info/top_level.txt
peeve-0.2.0.dist-info/RECORD
