Metadata-Version: 2.1
Name: peeve
Version: 0.2.0
Summary: Script launcher with automatic installation of dependencies
Home-page: https://github.com/comabrewer/peeve
Author: Marco Weber
Author-email: marco.weber@hotmail.de
License: MIT
Platform: UNKNOWN
Requires-Python: >=3.7
Provides-Extra: dev
Requires-Dist: black ; extra == 'dev'
Requires-Dist: flake8 ; extra == 'dev'
Requires-Dist: flake8-docstrings ; extra == 'dev'
Requires-Dist: isort ; extra == 'dev'
Requires-Dist: mypy ; extra == 'dev'
Requires-Dist: pylint ; extra == 'dev'
Provides-Extra: test
Requires-Dist: pytest ; extra == 'test'
